diseno/control_finca.v
/*
 * Generated by Digital. Don't modify this file!
 * Any changes will be lost if this file is regenerated.
 */

module control_finca (
  input I0_2,
  input I0_3,
  input I0_4,
  input I0_1,
  output Q0_1,
  output Q0_2,
  output Q0_4,
  output Q0_3,
  output Q0_5,
  output Q0_6,
  output Q0_7
);
  wire nP;
  wire Q0_4_temp;
  assign nP = ~ I0_4;
  assign Q0_3 = ~ I0_2;
  assign Q0_1 = ((I0_3 | ~ I0_1) & nP & I0_2);
  assign Q0_4_temp = ((I0_1 | I0_2) & nP);
  assign Q0_2 = Q0_4_temp;
  assign Q0_4 = Q0_4_temp;
  assign Q0_5 = I0_1;
  assign Q0_6 = I0_3;
  assign Q0_7 = I0_4;
endmodule

diseno/control_finca_tb.v
//  A testbench for control_finca_tb
`timescale 1us/1ns

module control_finca_tb;
    reg I0_2;
    reg I0_3;
    reg I0_4;
    reg I0_1;
    wire Q0_1;
    wire Q0_2;
    wire Q0_4;
    wire Q0_3;
    wire Q0_5;
    wire Q0_6;
    wire Q0_7;

  control_finca control_finca0 (
    .I0_2(I0_2),
    .I0_3(I0_3),
    .I0_4(I0_4),
    .I0_1(I0_1),
    .Q0_1(Q0_1),
    .Q0_2(Q0_2),
    .Q0_4(Q0_4),
    .Q0_3(Q0_3),
    .Q0_5(Q0_5),
    .Q0_6(Q0_6),
    .Q0_7(Q0_7)
  );

    reg [10:0] patterns[0:15];
    integer i;

    initial begin
      patterns[0] = 11'b0_0_0_0_0_0_0_0_1_0_0;
      patterns[1] = 11'b0_0_0_1_0_0_1_1_1_1_0;
      patterns[2] = 11'b0_0_1_0_0_0_0_1_0_1_1;
      patterns[3] = 11'b0_0_1_1_0_0_1_1_0_1_0;
      patterns[4] = 11'b0_1_0_0_0_1_0_0_1_0_0;
      patterns[5] = 11'b0_1_0_1_0_1_1_1_1_1_0;
      patterns[6] = 11'b0_1_1_0_0_1_0_1_0_1_1;
      patterns[7] = 11'b0_1_1_1_0_1_1_1_0_1_1;
      patterns[8] = 11'b1_0_0_0_1_0_0_0_1_0_0;
      patterns[9] = 11'b1_0_0_1_1_0_1_0_1_0_0;
      patterns[10] = 11'b1_0_1_0_1_0_0_0_0_0_0;
      patterns[11] = 11'b1_0_1_1_1_0_1_0_0_0_0;
      patterns[12] = 11'b1_1_0_0_1_1_0_0_1_0_0;
      patterns[13] = 11'b1_1_0_1_1_1_1_0_1_0_0;
      patterns[14] = 11'b1_1_1_0_1_1_0_0_0_0_0;
      patterns[15] = 11'b1_1_1_1_1_1_1_0_0_0_0;

      for (i = 0; i < 16; i = i + 1)
      begin
        I0_4 = patterns[i][10];
        I0_3 = patterns[i][9];
        I0_2 = patterns[i][8];
        I0_1 = patterns[i][7];
        #10;
        if (patterns[i][6] !== 1'hx)
        begin
          if (Q0_7 !== patterns[i][6])
          begin
            $display("%d:Q0_7: (assertion error). Expected %h, found %h", i, patterns[i][6], Q0_7);
            $finish;
          end
        end
        if (patterns[i][5] !== 1'hx)
        begin
          if (Q0_6 !== patterns[i][5])
          begin
            $display("%d:Q0_6: (assertion error). Expected %h, found %h", i, patterns[i][5], Q0_6);
            $finish;
          end
        end
        if (patterns[i][4] !== 1'hx)
        begin
          if (Q0_5 !== patterns[i][4])
          begin
            $display("%d:Q0_5: (assertion error). Expected %h, found %h", i, patterns[i][4], Q0_5);
            $finish;
          end
        end
        if (patterns[i][3] !== 1'hx)
        begin
          if (Q0_4 !== patterns[i][3])
          begin
            $display("%d:Q0_4: (assertion error). Expected %h, found %h", i, patterns[i][3], Q0_4);
            $finish;
          end
        end
        if (patterns[i][2] !== 1'hx)
        begin
          if (Q0_3 !== patterns[i][2])
          begin
            $display("%d:Q0_3: (assertion error). Expected %h, found %h", i, patterns[i][2], Q0_3);
            $finish;
          end
        end
        if (patterns[i][1] !== 1'hx)
        begin
          if (Q0_2 !== patterns[i][1])
          begin
            $display("%d:Q0_2: (assertion error). Expected %h, found %h", i, patterns[i][1], Q0_2);
            $finish;
          end
        end
        if (patterns[i][0] !== 1'hx)
        begin
          if (Q0_1 !== patterns[i][0])
          begin
            $display("%d:Q0_1: (assertion error). Expected %h, found %h", i, patterns[i][0], Q0_1);
            $finish;
          end
        end
      end

      $display("All tests passed.");
    end

    // Grabacion de la forma de onda.
    // El testbench exportado por Digital no incluye estas lineas, asi que
    // sin ellas vvp corre la simulacion pero no deja ningun archivo.
    // $dumpfile dice como se llama el archivo de salida.
    // $dumpvars(0, control_finca_tb) graba todas las senales desde este
    // modulo hacia adentro; el 0 significa "todos los niveles de jerarquia",
    // o sea que tambien quedan registradas las senales internas del diseno.
    initial begin
        $dumpfile("tb.vcd");
        $dumpvars(0, control_finca_tb);
    end

endmodule

simulacion/tb.vcd
$date
	Tue Oct  6 14:13:13 2026
$end
$version
	Icarus Verilog
$end
$timescale
	1ns
$end
$scope module control_finca_tb $end
$var wire 1 ! Q0_7 $end
$var wire 1 " Q0_6 $end
$var wire 1 # Q0_5 $end
$var wire 1 $ Q0_4 $end
$var wire 1 % Q0_3 $end
$var wire 1 & Q0_2 $end
$var wire 1 ' Q0_1 $end
$var reg 1 ( I0_1 $end
$var reg 1 ) I0_2 $end
$var reg 1 * I0_3 $end
$var reg 1 + I0_4 $end
$var integer 32 , i [31:0] $end
$scope module control_finca0 $end
$var wire 1 ( I0_1 $end
$var wire 1 ) I0_2 $end
$var wire 1 * I0_3 $end
$var wire 1 + I0_4 $end
$var wire 1 ' Q0_1 $end
$var wire 1 & Q0_2 $end
$var wire 1 % Q0_3 $end
$var wire 1 $ Q0_4 $end
$var wire 1 - Q0_4_temp $end
$var wire 1 # Q0_5 $end
$var wire 1 " Q0_6 $end
$var wire 1 ! Q0_7 $end
$var wire 1 . nP $end
$upscope $end
$upscope $end
$enddefinitions $end
$comment Show the parameter values. $end
$dumpall
$end
#0
$dumpvars
1.
0-
b0 ,
0+
0*
0)
0(
0'
0&
1%
0$
0#
0"
0!
$end
#10000
1&
1$
1-
1#
1(
b1 ,
#20000
1'
0%
0#
0(
1)
b10 ,
#30000
0'
1#
1(
b11 ,
#40000
0&
0$
0-
1%
0#
0(
0)
1"
1*
b100 ,
#50000
1&
1$
1-
1#
1(
b101 ,
#60000
0%
1'
0#
0(
1)
b110 ,
#70000
1#
1(
b111 ,
#80000
0&
0$
0-
1%
0'
0.
0#
0(
0)
0"
0*
1!
1+
b1000 ,
#90000
1#
1(
b1001 ,
#100000
0%
0#
0(
1)
b1010 ,
#110000
1#
1(
b1011 ,
#120000
1%
0#
0(
0)
1"
1*
b1100 ,
#130000
1#
1(
b1101 ,
#140000
0%
0#
0(
1)
b1110 ,
#150000
1#
1(
b1111 ,
#160000
b10000 ,
